alpm_conf/__init__.py
alpm_conf/alpm_conf.py
alpm_conf/git.py
alpm_conf/packages.py
alpm_conf/tests/__init__.py
alpm_conf/tests/pkg_utils.py
alpm_conf/tests/test_alpm_conf.py
alpm_conf/tests/test_git.py
alpm_conf/tests/test_packages.py
alpm_conf-0.5.dist-info/entry_points.txt
alpm_conf-0.5.dist-info/licenses/LICENSE
alpm_conf-0.5.dist-info/WHEEL
alpm_conf-0.5.dist-info/METADATA
alpm_conf-0.5.dist-info/RECORD
