Metadata-Version: 2.4
Name: alpm-conf
Version: 0.5
Summary: ArchLinux tool to manage /etc configuration files using git.
Keywords: Archlinux,pacman,alpm
Author-email: Xavier de Gaye <xdegaye@gmail.com>
Requires-Python: >=3.12,<4
Classifier: Development Status :: 2 - Pre-Alpha
Classifier: License :: OSI Approved :: MIT License
Classifier: Operating System :: Unix
Classifier: Programming Language :: Python :: 3
Classifier: Topic :: System :: Systems Administration
License-File: LICENSE
Project-URL: Changelog, https://alpm-conf.readthedocs.io/en/stable/history.html
Project-URL: Documentation, https://alpm-conf.readthedocs.io/en/stable/
Project-URL: Source, https://gitlab.com/xdegaye/alpm-conf
